mcp_playwright_scraper/__init__.py
mcp_playwright_scraper/server.py
mcp_playwright_scraper-0.1.0.dist-info/METADATA
mcp_playwright_scraper-0.1.0.dist-info/WHEEL
mcp_playwright_scraper-0.1.0.dist-info/entry_points.txt
mcp_playwright_scraper-0.1.0.dist-info/licenses/LICENSE
mcp_playwright_scraper-0.1.0.dist-info/RECORD
