Metadata-Version: 2.4
Name: mcp-playwright-scraper
Version: 0.1.0
Summary: A MCP server that scrapes web content to markdown using Playwright
Author-email: Dennis Lin <me@dennislin.io>
License-File: LICENSE
Requires-Python: >=3.11
Requires-Dist: beautifulsoup4
Requires-Dist: mcp>=1.1.2
Requires-Dist: playwright
Requires-Dist: pypandoc
